masky/__init__.py
masky/core.py
masky/bin/Masky.exe
masky/bin/__init__.py
masky/lib/__init__.py
masky/lib/results.py
masky/lib/smb.py
masky/lib/cert/__init__.py
masky/lib/cert/auth.py
masky/lib/cert/certificate.py
masky/lib/cert/errors.py
masky/lib/cert/misc.py
masky/lib/cert/pkinit.py
masky/lib/cert/structs.py
masky/ui/__init__.py
masky/ui/console.py
masky/ui/main.py
masky/ui/options.py
masky/utils/__init__.py
masky/utils/logger.py
masky/utils/targets.py
masky/utils/threadpool.py
masky/utils/toolbox.py
masky/utils/tracker.py
masky-0.2.1.dist-info/licenses/LICENSE
masky-0.2.1.dist-info/METADATA
masky-0.2.1.dist-info/WHEEL
masky-0.2.1.dist-info/entry_points.txt
masky-0.2.1.dist-info/top_level.txt
masky-0.2.1.dist-info/RECORD
