Metadata-Version: 2.4
Name: masky
Version: 0.2.1
Summary: Python library with CLI allowing to remotely dump domain user credentials via an ADCS
Author: Zak
License: MIT
Requires-Python: >=3.6
License-File: LICENSE
Requires-Dist: colorama
Requires-Dist: impacket
Requires-Dist: cryptography>=3.5
Requires-Dist: pyasn1
Requires-Dist: asn1crypto
Requires-Dist: importlib_resources; python_version < "3.9"
Dynamic: author
Dynamic: description
Dynamic: description-content-type
Dynamic: license
Dynamic: license-file
Dynamic: requires-dist
Dynamic: requires-python
Dynamic: summary
